{
  "project_info": {
    "project_number": "615080796143",
    "project_id": "recipebook-7385d",
    "storage_bucket": "recipebook-7385d.firebasestorage.app"
  },
  "client": [
    {
      "client_info": {
        "mobilesdk_app_id": "1:615080796143:android:2afcf8b2b1331c2203a01a",
        "android_client_info": {
          "package_name": "com.example.recipebook"
        }
      },
      "oauth_client": [
        {
          "client_id": "615080796143-6iffo0v5c0eo14va5m7q1e40gs1fc6aa.apps.googleusercontent.com",
          "client_type": 1,
          "android_info": {
            "package_name": "com.example.recipebook",
            "certificate_hash": "63087dd404a36b0d91c7a649feaea3044210119c"
          }
        },
        {
          "client_id": "615080796143-k0775i4mgccpormrs3sidn3ums60dhso.apps.googleusercontent.com",
          "client_type": 3
        }
      ],
      "api_key": [
        {
          "current_key": "AIzaSyBDWCERD4KznV_mz_TeyfdQOFgU9zhLBfI"
        }
      ],
      "services": {
        "appinvite_service": {
          "other_platform_oauth_client": [
            {
              "client_id": "615080796143-k0775i4mgccpormrs3sidn3ums60dhso.apps.googleusercontent.com",
              "client_type": 3
            }
          ]
        }
      }
    }
  ],
  "configuration_version": "1"
}